[{
    "ID": "raise_repair",
    "Name": "Raise repair",
    "Description":"A short description of this tmeplaye and what needs it would meet should go here",
    "Fields": ["Address", "AlertRegardingLocation", "AlertRegardingPerson", "Attachment:BasicAttachment", "BasicAttachment", "Dependency", "Duration", "Keysafe", "PostalAddress:Address", "Property", "PropertyAddress:PostalAddress", "Quantity", "RateScheduleItem", "Reference", "Site", "Trade", "Unit", "WorkClass", "WorkClassSubType", "WorkElement", "WorkElementDependency:Dependency", "WorkOrder", "WorkOrderAccessInformation", "WorkPriority"],
    "Codelists": ["CostSubjectCode", "DependencyTypeCode", "LocationAlertTypeCode", "M3NHFScheduleOfRatesCode", "PersonAlertTypeCode", "TradeCode", "UNECEUnitOfMeasurementCode", "WorkClassCode", "WorkPriorityCode", "WorkType"]
},
{
    "ID": "view_repair",
    "Name": "View repair",
    "Description":"A short description of this tmeplaye and what needs it would meet should go here",
    "Fields": ["Address", "AlertRegardingLocation", "AlertRegardingPerson", "Attachment:BasicAttachment", "BasicAttachment", "Dependency", "Duration", "Keysafe", "PostalAddress:Address", "Property", "PropertyAddress:PostalAddress", "Quantity", "RateScheduleItem", "Reference", "Site", "Trade", "Unit", "WorkClass", "WorkClassSubType", "WorkElement", "WorkElementDependency:Dependency", "WorkOrder", "WorkOrderAccessInformation", "WorkPriority"],
    "Codelists": ["CostSubjectCode", "DependencyTypeCode", "LocationAlertTypeCode", "M3NHFScheduleOfRatesCode", "PersonAlertTypeCode", "TradeCode", "UNECEUnitOfMeasurementCode", "WorkClassCode", "WorkPriorityCode", "WorkType"]
},
{
    "ID": "view_repair",
    "Name": "View repair",
    "Description":"A short description of this tmeplaye and what needs it would meet should go here",
    "Fields": ["Address", "AlertRegardingLocation", "AlertRegardingPerson", "Attachment:BasicAttachment", "BasicAttachment", "Dependency", "Duration", "Keysafe", "PostalAddress:Address", "Property", "PropertyAddress:PostalAddress", "Quantity", "RateScheduleItem", "Reference", "Site", "Trade", "Unit", "WorkClass", "WorkClassSubType", "WorkElement", "WorkElementDependency:Dependency", "WorkOrder", "WorkOrderAccessInformation", "WorkPriority"],
    "Codelists": ["CostSubjectCode", "DependencyTypeCode", "LocationAlertTypeCode", "M3NHFScheduleOfRatesCode", "PersonAlertTypeCode", "TradeCode", "UNECEUnitOfMeasurementCode", "WorkClassCode", "WorkPriorityCode", "WorkType"]
},
{
    "ID": "view_repair",
    "Name": "View repair",
    "Description":"A short description of this tmeplaye and what needs it would meet should go here",
    "Fields": ["Address", "AlertRegardingLocation", "AlertRegardingPerson", "Attachment:BasicAttachment", "BasicAttachment", "Dependency", "Duration", "Keysafe", "PostalAddress:Address", "Property", "PropertyAddress:PostalAddress", "Quantity", "RateScheduleItem", "Reference", "Site", "Trade", "Unit", "WorkClass", "WorkClassSubType", "WorkElement", "WorkElementDependency:Dependency", "WorkOrder", "WorkOrderAccessInformation", "WorkPriority"],
    "Codelists": ["CostSubjectCode", "DependencyTypeCode", "LocationAlertTypeCode", "M3NHFScheduleOfRatesCode", "PersonAlertTypeCode", "TradeCode", "UNECEUnitOfMeasurementCode", "WorkClassCode", "WorkPriorityCode", "WorkType"]
},
{
    "ID": "view_repair",
    "Name": "View repair",
    "Description":"A short description of this tmeplaye and what needs it would meet should go here",
    "Fields": ["Address", "AlertRegardingLocation", "AlertRegardingPerson", "Attachment:BasicAttachment", "BasicAttachment", "Dependency", "Duration", "Keysafe", "PostalAddress:Address", "Property", "PropertyAddress:PostalAddress", "Quantity", "RateScheduleItem", "Reference", "Site", "Trade", "Unit", "WorkClass", "WorkClassSubType", "WorkElement", "WorkElementDependency:Dependency", "WorkOrder", "WorkOrderAccessInformation", "WorkPriority"],
    "Codelists": ["CostSubjectCode", "DependencyTypeCode", "LocationAlertTypeCode", "M3NHFScheduleOfRatesCode", "PersonAlertTypeCode", "TradeCode", "UNECEUnitOfMeasurementCode", "WorkClassCode", "WorkPriorityCode", "WorkType"]
},
{
    "ID": "view_repair",
    "Name": "View repair",
    "Description":"A short description of this tmeplaye and what needs it would meet should go here",
    "Fields": ["Address", "AlertRegardingLocation", "AlertRegardingPerson", "Attachment:BasicAttachment", "BasicAttachment", "Dependency", "Duration", "Keysafe", "PostalAddress:Address", "Property", "PropertyAddress:PostalAddress", "Quantity", "RateScheduleItem", "Reference", "Site", "Trade", "Unit", "WorkClass", "WorkClassSubType", "WorkElement", "WorkElementDependency:Dependency", "WorkOrder", "WorkOrderAccessInformation", "WorkPriority"],
    "Codelists": ["CostSubjectCode", "DependencyTypeCode", "LocationAlertTypeCode", "M3NHFScheduleOfRatesCode", "PersonAlertTypeCode", "TradeCode", "UNECEUnitOfMeasurementCode", "WorkClassCode", "WorkPriorityCode", "WorkType"]
},
{
    "ID": "view_repair",
    "Name": "View repair",
    "Description":"A short description of this tmeplaye and what needs it would meet should go here",
    "Fields": ["Address", "AlertRegardingLocation", "AlertRegardingPerson", "Attachment:BasicAttachment", "BasicAttachment", "Dependency", "Duration", "Keysafe", "PostalAddress:Address", "Property", "PropertyAddress:PostalAddress", "Quantity", "RateScheduleItem", "Reference", "Site", "Trade", "Unit", "WorkClass", "WorkClassSubType", "WorkElement", "WorkElementDependency:Dependency", "WorkOrder", "WorkOrderAccessInformation", "WorkPriority"],
    "Codelists": ["CostSubjectCode", "DependencyTypeCode", "LocationAlertTypeCode", "M3NHFScheduleOfRatesCode", "PersonAlertTypeCode", "TradeCode", "UNECEUnitOfMeasurementCode", "WorkClassCode", "WorkPriorityCode", "WorkType"]
},
{
    "ID": "view_repair",
    "Name": "View repair",
    "Description":"A short description of this tmeplaye and what needs it would meet should go here",
    "Fields": ["Address", "AlertRegardingLocation", "AlertRegardingPerson", "Attachment:BasicAttachment", "BasicAttachment", "Dependency", "Duration", "Keysafe", "PostalAddress:Address", "Property", "PropertyAddress:PostalAddress", "Quantity", "RateScheduleItem", "Reference", "Site", "Trade", "Unit", "WorkClass", "WorkClassSubType", "WorkElement", "WorkElementDependency:Dependency", "WorkOrder", "WorkOrderAccessInformation", "WorkPriority"],
    "Codelists": ["CostSubjectCode", "DependencyTypeCode", "LocationAlertTypeCode", "M3NHFScheduleOfRatesCode", "PersonAlertTypeCode", "TradeCode", "UNECEUnitOfMeasurementCode", "WorkClassCode", "WorkPriorityCode", "WorkType"]
},
{
    "ID": "view_repair",
    "Name": "View repair",
    "Description":"A short description of this tmeplaye and what needs it would meet should go here",
    "Fields": ["Address", "AlertRegardingLocation", "AlertRegardingPerson", "Attachment:BasicAttachment", "BasicAttachment", "Dependency", "Duration", "Keysafe", "PostalAddress:Address", "Property", "PropertyAddress:PostalAddress", "Quantity", "RateScheduleItem", "Reference", "Site", "Trade", "Unit", "WorkClass", "WorkClassSubType", "WorkElement", "WorkElementDependency:Dependency", "WorkOrder", "WorkOrderAccessInformation", "WorkPriority"],
    "Codelists": ["CostSubjectCode", "DependencyTypeCode", "LocationAlertTypeCode", "M3NHFScheduleOfRatesCode", "PersonAlertTypeCode", "TradeCode", "UNECEUnitOfMeasurementCode", "WorkClassCode", "WorkPriorityCode", "WorkType"]
},
{
    "ID": "view_repair",
    "Name": "View repair",
    "Description":"A short description of this tmeplaye and what needs it would meet should go here",
    "Fields": ["Address", "AlertRegardingLocation", "AlertRegardingPerson", "Attachment:BasicAttachment", "BasicAttachment", "Dependency", "Duration", "Keysafe", "PostalAddress:Address", "Property", "PropertyAddress:PostalAddress", "Quantity", "RateScheduleItem", "Reference", "Site", "Trade", "Unit", "WorkClass", "WorkClassSubType", "WorkElement", "WorkElementDependency:Dependency", "WorkOrder", "WorkOrderAccessInformation", "WorkPriority"],
    "Codelists": ["CostSubjectCode", "DependencyTypeCode", "LocationAlertTypeCode", "M3NHFScheduleOfRatesCode", "PersonAlertTypeCode", "TradeCode", "UNECEUnitOfMeasurementCode", "WorkClassCode", "WorkPriorityCode", "WorkType"]
},
{
    "ID": "view_repair",
    "Name": "View repair",
    "Description":"A short description of this tmeplaye and what needs it would meet should go here",
    "Fields": ["Address", "AlertRegardingLocation", "AlertRegardingPerson", "Attachment:BasicAttachment", "BasicAttachment", "Dependency", "Duration", "Keysafe", "PostalAddress:Address", "Property", "PropertyAddress:PostalAddress", "Quantity", "RateScheduleItem", "Reference", "Site", "Trade", "Unit", "WorkClass", "WorkClassSubType", "WorkElement", "WorkElementDependency:Dependency", "WorkOrder", "WorkOrderAccessInformation", "WorkPriority"],
    "Codelists": ["CostSubjectCode", "DependencyTypeCode", "LocationAlertTypeCode", "M3NHFScheduleOfRatesCode", "PersonAlertTypeCode", "TradeCode", "UNECEUnitOfMeasurementCode", "WorkClassCode", "WorkPriorityCode", "WorkType"]
},
{
    "ID": "view_repair",
    "Name": "View repair",
    "Description":"A short description of this tmeplaye and what needs it would meet should go here",
    "Fields": ["Address", "AlertRegardingLocation", "AlertRegardingPerson", "Attachment:BasicAttachment", "BasicAttachment", "Dependency", "Duration", "Keysafe", "PostalAddress:Address", "Property", "PropertyAddress:PostalAddress", "Quantity", "RateScheduleItem", "Reference", "Site", "Trade", "Unit", "WorkClass", "WorkClassSubType", "WorkElement", "WorkElementDependency:Dependency", "WorkOrder", "WorkOrderAccessInformation", "WorkPriority"],
    "Codelists": ["CostSubjectCode", "DependencyTypeCode", "LocationAlertTypeCode", "M3NHFScheduleOfRatesCode", "PersonAlertTypeCode", "TradeCode", "UNECEUnitOfMeasurementCode", "WorkClassCode", "WorkPriorityCode", "WorkType"]
},
{
    "ID": "view_repair",
    "Name": "View repair",
    "Description":"A short description of this tmeplaye and what needs it would meet should go here",
    "Fields": ["Address", "AlertRegardingLocation", "AlertRegardingPerson", "Attachment:BasicAttachment", "BasicAttachment", "Dependency", "Duration", "Keysafe", "PostalAddress:Address", "Property", "PropertyAddress:PostalAddress", "Quantity", "RateScheduleItem", "Reference", "Site", "Trade", "Unit", "WorkClass", "WorkClassSubType", "WorkElement", "WorkElementDependency:Dependency", "WorkOrder", "WorkOrderAccessInformation", "WorkPriority"],
    "Codelists": ["CostSubjectCode", "DependencyTypeCode", "LocationAlertTypeCode", "M3NHFScheduleOfRatesCode", "PersonAlertTypeCode", "TradeCode", "UNECEUnitOfMeasurementCode", "WorkClassCode", "WorkPriorityCode", "WorkType"]
}
]